{
  "name": "sesion",
  "base": "PersistedModel",
  "strict": false,
  "idInjection": false,
  "options": {
    "validateUpsert": true
  },
  "properties": {
    "id": {
      "type": "string",
      "id": true
    },
    "fechaHora": {
      "type": "date",
      "required": true
    },
    "activo": {
      "type": "boolean",
      "required": true
    }
  },
  "validations": [],
  "relations": {
    "usuarios": {
      "type": "hasOne",
      "model": "usuario",
      "foreignKey": "usuarioId"
    }
  },
  "acls": [],
  "methods": {}
}
